ediblepaste/__init__.py
ediblepaste/config.py
ediblepaste/ediblepaste.py
ediblepaste-1.2.1.dist-info/METADATA
ediblepaste-1.2.1.dist-info/RECORD
ediblepaste-1.2.1.dist-info/WHEEL
ediblepaste-1.2.1.dist-info/top_level.txt
