Metadata-Version: 2.1
Name: ediblepaste
Version: 1.2.1
Summary: Wrapper for paste sites API
Home-page: http://github.com/ediblesushi/ediblepaste
Author: Chris Doucette
Author-email: chrisdoucette15@gmail.com
License: UNKNOWN
Platform: UNKNOWN
Classifier: Programming Language :: Python :: 3
Classifier: License :: OSI Approved :: MIT License
Classifier: Operating System :: OS Independent
